lcg/__init__.py
lcg/content.py
lcg/exercises.py
lcg/i18n.py
lcg/locales.py
lcg/make.py
lcg/nodes.py
lcg/parse.py
lcg/plot.py
lcg/presentation.py
lcg/read.py
lcg/resources.py
lcg/test.py
lcg/transform.py
lcg/units.py
lcg/util.py
lcg/widgets.py
lcg/export/__init__.py
lcg/export/braille.py
lcg/export/epub.py
lcg/export/exercises_html.py
lcg/export/export.py
lcg/export/hhp.py
lcg/export/html.py
lcg/export/ims.py
lcg/export/mathml.py
lcg/export/nemeth.py
lcg/export/pdf.py
lcg/export/braille-tables/lcg.utb
lcg/export/styles/presentation-braille-test.py
lcg/export/styles/presentation-braille.py
lcg/resources/css/default.css
lcg/resources/css/epub.css
lcg/resources/css/lcg-exercises.css
lcg/resources/css/lcg-widgets.css
lcg/resources/css/photoswipe.css
lcg/resources/css/pygments.css
lcg/resources/flash/jplayer.swf
lcg/resources/images/jplayer-seeking.gif
lcg/resources/images/lcg-icons.png
lcg/resources/media/exercise-responses/cs/correct-01.mp3
lcg/resources/media/exercise-responses/cs/correct-02.mp3
lcg/resources/media/exercise-responses/cs/correct-03.mp3
lcg/resources/media/exercise-responses/cs/correct-04.mp3
lcg/resources/media/exercise-responses/cs/correct-05.mp3
lcg/resources/media/exercise-responses/cs/correct-06.mp3
lcg/resources/media/exercise-responses/cs/correct-07.mp3
lcg/resources/media/exercise-responses/cs/correct-08.mp3
lcg/resources/media/exercise-responses/cs/correct-09.mp3
lcg/resources/media/exercise-responses/cs/correct-10.mp3
lcg/resources/media/exercise-responses/cs/correct-11.mp3
lcg/resources/media/exercise-responses/cs/correct-12.mp3
lcg/resources/media/exercise-responses/cs/correct-13.mp3
lcg/resources/media/exercise-responses/cs/correct-14.mp3
lcg/resources/media/exercise-responses/cs/correct-15.mp3
lcg/resources/media/exercise-responses/cs/correct-16.mp3
lcg/resources/media/exercise-responses/cs/correct-17.mp3
lcg/resources/media/exercise-responses/cs/correct-18.mp3
lcg/resources/media/exercise-responses/cs/correct-19.mp3
lcg_framework-0.7.0.dist-info/licenses/COPYING
lcg_framework-0.7.0.dist-info/WHEEL
lcg_framework-0.7.0.dist-info/METADATA
lcg_framework-0.7.0.dist-info/RECORD
