Metadata-Version: 2.4
Name: lcg-framework
Version: 0.7.0
Summary: LCG — Python library for content abstraction and multi-format document processing
Author-email: Tomas Cerha <cerha@truecode.cz>, Milan Zamazal <pdm@zamazal.org>
Requires-Python: >=2.7
Classifier: Programming Language :: Python :: 2.7
Classifier: Programming Language :: Python :: 3.5
Classifier: License :: OSI Approved :: GNU General Public License v2 or later (GPLv2+)
License-File: COPYING
Requires-Dist: future
Requires-Dist: pygments
Requires-Dist: pillow
Requires-Dist: reportlab ; extra == "all"
Requires-Dist: matplotlib ; extra == "all"
Requires-Dist: pandas ; extra == "all"
Requires-Dist: svglib ; extra == "all"
Requires-Dist: cairosvg==0.5 ; extra == "all"
Requires-Dist: pycairo ; extra == "all"
Requires-Dist: louis ; extra == "braille"
Requires-Dist: reportlab ; extra == "pdf"
Requires-Dist: matplotlib ; extra == "plot"
Requires-Dist: pandas ; extra == "plot"
Requires-Dist: svglib ; extra == "plot"
Requires-Dist: cairosvg==0.5 ; extra == "plot"
Requires-Dist: pycairo ; extra == "plot"
Provides-Extra: all
Provides-Extra: braille
Provides-Extra: pdf
Provides-Extra: plot
